heketi/__init__.py
heketi/heketi.py
heketi-3.0.0.dist-info/DESCRIPTION.rst
heketi-3.0.0.dist-info/METADATA
heketi-3.0.0.dist-info/RECORD
heketi-3.0.0.dist-info/WHEEL
heketi-3.0.0.dist-info/metadata.json
heketi-3.0.0.dist-info/top_level.txt
