Metadata-Version: 2.0
Name: heketi
Version: 3.0.0
Summary: Python client library for Heketi
Home-page: https://github.com/heketi/heketi/tree/master/client/api/python
Author: Luis Pabon
Author-email: lpabon@redhat.com
License: Apache License (2.0)
Platform: UNKNOWN
Classifier: Development Status :: 5 - Production/Stable
Classifier: Intended Audience :: Information Technology
Classifier: Intended Audience :: System Administrators
Classifier: License :: OSI Approved :: Apache Software License
Classifier: Operating System :: POSIX :: Linux
Classifier: Programming Language :: Python
Classifier: Programming Language :: Python :: 2.7
Classifier: Topic :: System :: Filesystems
Classifier: Topic :: System :: Distributed Computing
Requires-Dist: pyjwt
Requires-Dist: requests
